game_hero/__init__.py
game_hero/game_characters.py
game_hero/game_constants.py
game_hero/gameplay_mechanics.py
game_hero/main_game.py
tests/__init__.py
tests/test_game_characters.py
tests/test_gameplay_mechanics.py
tests/test_main_game.py
game_hero-1.0.0.dist-info/LICENSE
game_hero-1.0.0.dist-info/METADATA
game_hero-1.0.0.dist-info/WHEEL
game_hero-1.0.0.dist-info/top_level.txt
game_hero-1.0.0.dist-info/RECORD
