Metadata-Version: 2.1
Name: game-hero
Version: 1.0.0
Summary: A HeroGame implemented for demonstration purposes
Home-page: https://github.com/sandu-alexandru/hero_game/
Author: Alexandru Sandu
Author-email: sandualex7@gmail.com
License: UNKNOWN
Platform: UNKNOWN
Classifier: Programming Language :: Python :: 3
Requires-Python: >=3.6
